{"cameraMode":{"drawMode":0,"name":"Shaded","section":"Shading Mode"},"sceneLighting":false,"audioPlay":false,"sceneViewState":{"showFog":true,"showMaterialUpdate":false,"showSkybox":false,"showFlares":true,"showImageEffects":true,"showParticleSystems":true},"in2DMode":false,"pivot":{"x":-2.384185791015625e-7,"y":0.33217787742614748,"z":2.384185791015625e-7},"rotation":{"x":0.11748936772346497,"y":-0.5970040559768677,"z":0.08894499391317368,"w":0.7885887622833252},"size":4.94659948348999,"orthographic":false}